<?xml version="1.0" encoding="UTF-8"?>
<!DOCTYPE markables SYSTEM "markables.dtd">
<markables xmlns="www.eml.org/NameSpaces/target">
<markable id="markable_100500275" span="word_1234..word_1236" mmax_level="target"  anaphref="empty"  sentiment_ref="empty"  preferred="true" />
<markable id="markable_8" span="word_142" mmax_level="target"  anaphref="empty"  sentiment_ref="empty"  preferred="true" />
<markable id="markable_100500264" span="word_284" mmax_level="target"  anaphref="empty"  sentiment_ref="empty"  preferred="true" />
<markable id="markable_81" span="word_525" mmax_level="target"  sentiment_ref="empty"  preferred="true" />
<markable id="markable_34" span="word_1201" mmax_level="target"  anaphref="empty"  sentiment_ref="empty"  preferred="true" />
<markable id="markable_100" span="word_940" mmax_level="target"  anaphref="empty"  sentiment_ref="empty"  preferred="true" />
<markable id="markable_100500261" span="word_68..word_69" mmax_level="target"  anaphref="empty"  sentiment_ref="empty"  preferred="true" />
<markable id="markable_39" span="word_1320" mmax_level="target"  anaphref="empty"  sentiment_ref="empty"  preferred="true" />
<markable id="markable_145" span="word_1229" mmax_level="target"  anaphref="empty"  sentiment_ref="empty"  preferred="true" />
<markable id="markable_100500268" span="word_507" mmax_level="target"  anaphref="markable_100500269"  sentiment_ref="empty"  preferred="true" />
<markable id="markable_187" span="word_784..word_791" mmax_level="target"  anaphref="empty"  sentiment_ref="empty"  preferred="true" />
<markable id="markable_100500269" span="word_504..word_517" mmax_level="target"  anaphref="empty"  sentiment_ref="empty"  preferred="true" />
<markable id="markable_42" span="word_1881..word_1887" mmax_level="target"  anaphref="empty"  sentiment_ref="empty"  preferred="true" />
<markable id="markable_32" span="word_999..word_1003" mmax_level="target"  anaphref="empty"  sentiment_ref="empty"  preferred="true" />
<markable id="markable_170" span="word_73..word_74" mmax_level="target"  anaphref="empty"  sentiment_ref="empty"  preferred="true" />
<markable id="markable_94" span="word_893..word_894" mmax_level="target"  anaphref="empty"  sentiment_ref="empty"  preferred="true" />
<markable id="markable_110" span="word_206" mmax_level="target"  anaphref="empty"  sentiment_ref="empty"  preferred="true" />
<markable id="markable_23" span="word_806" mmax_level="target"  anaphref="empty"  sentiment_ref="empty"  preferred="true" />
<markable id="markable_174" span="word_102" mmax_level="target"  anaphref="empty"  sentiment_ref="empty"  preferred="true" />
<markable id="markable_97" span="word_862..word_863" mmax_level="target"  anaphref="empty"  sentiment_ref="empty"  preferred="true" />
<markable id="markable_152" span="word_1256" mmax_level="target"  anaphref="empty"  sentiment_ref="empty"  preferred="true" />
<markable id="markable_173" span="word_76..word_77" mmax_level="target"  anaphref="empty"  sentiment_ref="empty"  preferred="true" />
<markable id="markable_179" span="word_276" mmax_level="target"  anaphref="empty"  sentiment_ref="empty"  preferred="true" />
<markable id="markable_177" span="word_142" mmax_level="target"  anaphref="empty"  sentiment_ref="empty"  preferred="true" />
</markables>